neuropipeline/__init__.py
neuropipeline/base.py
neuropipeline/eeg.py
neuropipeline/fnirs.py
neuropipeline/test.py
neuropipeline/utils.py
neuropipeline-0.1.3.dist-info/METADATA
neuropipeline-0.1.3.dist-info/WHEEL
neuropipeline-0.1.3.dist-info/top_level.txt
neuropipeline-0.1.3.dist-info/RECORD
