Metadata-Version: 2.1
Name: neuropipeline
Version: 0.1.3
Summary: A short description of your package
Home-page: https://github.com/adamaske/neuropipeline
Author: Adam Emile Aske
Author-email: adamaske@live.no
Project-URL: Bug Tracker, https://github.com/adamaske/neuropipeline/issues
Classifier: Programming Language :: Python :: 3.8
Classifier: License :: OSI Approved :: MIT License
Classifier: Operating System :: OS Independent
